[
  {
    "id": "655a2067cb3ab102455d131c",
    "author_picture": "https://randomuser.me/api/portraits/men/60.jpg",
    "picture": "https://img.freepik.com/premium-photo/developing-programmer-development-website-design-coding-technologies_18497-1090.jpg?size=626&ext=jpg&ga=GA1.1.385506669.1696431992&semt=sph",
    "title": "How to get your first job as a self-taught programmer",
    "name": "Carroll Day",
    "redTime": 10,
    "address": "346 Tennis Court, Brambleton, Hawaii, 8191",
    "registered": "2014-08-08T12:05:35 +07:00"
  },
  {
    "id": "655a206784744703cbb7f28a",
    "author_picture": "https://randomuser.me/api/portraits/men/64.jpg",
    "picture": "https://img.freepik.com/free-photo/rear-view-programmer-working-all-night-long_1098-18697.jpg?size=626&ext=jpg&ga=GA1.1.385506669.1696431992&semt=sph",
    "title": "Talk to as many people as you can who have accomplished what you want to accomplish.",
    "name": "Greene Mcneil",
    "redTime": 9,
    "address": "444 Provost Street, Williamson, Arizona, 9806",
    "registered": "2017-09-07T08:45:33 +07:00"
  },
  {
    "id": "655a206737c924ab65f70b44",
    "author_picture": "https://randomuser.me/api/portraits/men/66.jpg",
    "picture": "https://img.freepik.com/free-photo/person-front-computer-working-html_23-2150040428.jpg?size=626&ext=jpg&ga=GA1.1.385506669.1696431992&semt=sph",
    "title": "Start interviewing as soon as possible.",
    "name": "Shanna Barry",
    "redTime": 7,
    "address": "852 Wolf Place, Kieler, South Dakota, 2430",
    "registered": "2018-07-10T03:46:25 +07:00"
  },
  {
    "id": "655a2067c1a13b19b4e5829a",
    "author_picture": "https://randomuser.me/api/portraits/men/76.jpg",
    "picture": "https://img.freepik.com/free-vector/laptop-with-program-code-isometric-icon-software-development-programming-applications-dark-neon_39422-971.jpg?size=626&ext=jpg&ga=GA1.1.385506669.1696431992&semt=sph",
    "title": "Start gaining experience while you learn, in whatever ways you can",
    "name": "Kane Chavez",
    "redTime": 10,
    "address": "987 Amherst Street, Emory, West Virginia, 2598",
    "registered": "2016-08-14T05:10:04 +07:00"
  },
  {
    "id": "655a2067d513093af51e698a",
    "author_picture": "https://randomuser.me/api/portraits/men/24.jpg",
    "picture": "https://img.freepik.com/free-photo/html-system-websites-concept_23-2150323528.jpg?size=626&ext=jpg&ga=GA1.1.385506669.1696431992&semt=sph",
    "title": "Learn what opportunity is out there – then learn accordingly.",
    "name": "Goodwin King",
    "redTime": 7,
    "address": "522 Hall Street, Brenton, Ohio, 3585",
    "registered": "2022-02-09T06:14:04 +08:00"
  }
]
